scripts/__init__.py
scripts/gen_lcp.py
scripts/search_st2.py
scripts/utils.py
pat_match_st2-1.0.0.dist-info/LICENSE
pat_match_st2-1.0.0.dist-info/METADATA
pat_match_st2-1.0.0.dist-info/WHEEL
pat_match_st2-1.0.0.dist-info/entry_points.txt
pat_match_st2-1.0.0.dist-info/top_level.txt
pat_match_st2-1.0.0.dist-info/RECORD
