Metadata-Version: 2.1
Name: pat-match-st2
Version: 1.0.0
Summary: pattern matching tools
Home-page: https://github.com/balrajsingh9/gsa-projects
Author: Balraj Singh Saini, Chahat Gupta, Janardhan Jayachandra Kammath
Author-email: au671472@post.au.dk
License: MIT
Platform: UNKNOWN
Classifier: Programming Language :: Python :: 3.9
Classifier: License :: OSI Approved :: MIT License
Classifier: Operating System :: OS Independent
License-File: LICENSE
Requires-Dist: biopython
